[{
    "Functinal Grouping": [
        "Button",
        {
            "Input": [
                "Label",
                "Slider",
                "SelectMenu",
                "Checkbox",
                "OptionHeader",
                {
                    "Text": ["TextInput", "TextArea" ],
                    "Boolean": ["ToggleSwitch", "RadioButton", "Switch"],
                    "Date & Time": ["DateTimePicker", "CalendarPicker"],
                    "Color": ["ColorPicker", "ColorPickerButton", "ColorPalette",
                        "ColorTitle", "HsvPicker"]
                }
            ],
            "Output": ["ProgressBar"],
            "Layout": [ "Header","Footer", "ButtonGroup", "RadioGroup", "CheckboxGroup",
                "Form", "List", "ListItem", "ListDivider", "ListButton", "OrderedList",
                "Grid", "Block", "Accordion", "Collapsible"]

        }
    ],

    "Widget Sets": [
        {
            "jQuery Mobile": [ "Button", "Label", "Slider", "SelectMenu",
                "Checkbox","TextInput", "TextArea", "ToggleSwitch",
                "RadioButton" , "Header","Footer", "ButtonGroup", "RadioGroup", "CheckboxGroup",
                "Form", "List", "ListItem", "ListDivider", "ListButton", "OrderedList",
                "Grid", "Block", "Accordion", "Collapsible"
            ],
            "Tizen Widgets": [ "OptionHeader",  "Switch","DateTimePicker",
                "CalendarPicker", "ColorPicker", "ColorPickerButton",
                "ColorPalette", "ColorTitle", "HsvPicker", "ProgressBar"
            ]
        }
    ]
}]
